{
  "qafm": {
    "PSNR": 31.7056,
    "PSNR_trigger_only": 41.8397,
    "SSIM": 0.9684,
    "SSIM_trigger_only": 0.9958,
    "LPIPS": 0.0018,
    "LPIPS_trigger_only": 0.0003,
    "PSNR_std": 1.5801,
    "n_samples": 1000,
    "PSNR_ok": false,
    "SSIM_ok": true,
    "LPIPS_ok": true
  },
  "badnets": {
    "PSNR": 28.4036,
    "PSNR_trigger_only": 28.4036,
    "SSIM": 0.9667,
    "SSIM_trigger_only": 0.9667,
    "LPIPS": 0.001,
    "LPIPS_trigger_only": 0.001,
    "PSNR_std": 10.6837,
    "n_samples": 1000,
    "PSNR_ok": false,
    "SSIM_ok": false,
    "LPIPS_ok": true
  },
  "ftrojan": {
    "PSNR": 45.3077,
    "PSNR_trigger_only": 45.3077,
    "SSIM": 0.9981,
    "SSIM_trigger_only": 0.9981,
    "LPIPS": 0.0,
    "LPIPS_trigger_only": 0.0,
    "PSNR_std": 0.0742,
    "n_samples": 1000,
    "PSNR_ok": true,
    "SSIM_ok": true,
    "LPIPS_ok": true
  },
  "blended": {
    "PSNR": 28.3825,
    "PSNR_trigger_only": 28.3825,
    "SSIM": 0.9297,
    "SSIM_trigger_only": 0.9297,
    "LPIPS": 0.0033,
    "LPIPS_trigger_only": 0.0033,
    "PSNR_std": 0.8943,
    "n_samples": 1000,
    "PSNR_ok": false,
    "SSIM_ok": false,
    "LPIPS_ok": true
  }
}